{"stats":{"minecraft:custom":{"minecraft:mob_kills":13,"minecraft:inspect_hopper":5,"minecraft:interact_with_crafting_table":15,"minecraft:open_shulker_box":17,"minecraft:bell_ring":24,"minecraft:leave_game":7,"minecraft:time_since_death":33525,"minecraft:climb_one_cm":5178,"minecraft:sprint_one_cm":124258,"minecraft:walk_one_cm":3023341,"minecraft:drop":462,"minecraft:damage_dealt_absorbed":101,"minecraft:talked_to_villager":22,"minecraft:deaths":24,"minecraft:sneak_time":15649,"minecraft:walk_under_water_one_cm":21796,"minecraft:boat_one_cm":368728,"minecraft:interact_with_lectern":2,"minecraft:jump":2448,"minecraft:walk_on_water_one_cm":19242,"minecraft:interact_with_furnace":2,"minecraft:tune_noteblock":12,"minecraft:play_one_minute":1497251,"minecraft:interact_with_loom":14,"minecraft:pot_flower":3,"minecraft:time_since_rest":33570,"minecraft:damage_taken":35356,"minecraft:damage_absorbed":160,"minecraft:damage_dealt":986,"minecraft:swim_one_cm":61317,"minecraft:fly_one_cm":3330808,"minecraft:open_chest":16,"minecraft:crouch_one_cm":47599,"minecraft:fall_one_cm":317166,"minecraft:inspect_dispenser":1,"minecraft:horse_one_cm":469},"minecraft:used":{"minecraft:oak_fence":46,"minecraft:oak_trapdoor":1,"minecraft:iron_bars":20,"minecraft:petrified_oak_slab":1,"minecraft:trident":37,"minecraft:writable_book":5,"minecraft:light_gray_stained_glass_pane":14,"minecraft:flint_and_steel":23,"minecraft:armor_stand":3,"minecraft:carved_pumpkin":7,"minecraft:carrot_on_a_stick":8,"minecraft:red_concrete":150,"minecraft:redstone":84,"minecraft:oak_sign":3,"minecraft:chest":14,"minecraft:stone":3,"minecraft:white_shulker_box":4,"minecraft:wooden_shovel":308,"minecraft:bell":16,"minecraft:quartz_stairs":125,"minecraft:oak_door":10,"minecraft:torch":5,"minecraft:dirt":70,"minecraft:hopper":12,"minecraft:blue_stained_glass":53,"minecraft:prismarine_brick_stairs":4,"minecraft:oak_wood":1,"minecraft:yellow_carpet":3,"minecraft:jungle_trapdoor":4,"minecraft:cyan_wool":2,"minecraft:spruce_fence":28,"minecraft:light_blue_stained_glass":34,"minecraft:oak_fence_gate":1,"minecraft:dark_oak_planks":303,"minecraft:glass":2,"minecraft:red_shulker_box":2,"minecraft:sea_lantern":198,"minecraft:stripped_dark_oak_wood":1,"minecraft:bookshelf":2,"minecraft:quartz_pillar":35,"minecraft:quartz_slab":157,"minecraft:iron_block":58,"minecraft:lantern":23,"minecraft:grass_block":640,"minecraft:oak_stairs":15,"minecraft:quartz_block":209,"minecraft:dark_oak_wood":1,"minecraft:dark_oak_leaves":95,"minecraft:dark_oak_slab":233,"minecraft:smooth_quartz":1,"minecraft:totem_of_undying":3,"minecraft:stone_brick_stairs":4,"minecraft:stone_bricks":1,"minecraft:repeater":72,"minecraft:item_frame":16,"minecraft:bamboo":4,"minecraft:bedrock":1,"minecraft:red_carpet":156,"minecraft:glowstone":5,"minecraft:redstone_lamp":1,"minecraft:brown_carpet":8,"minecraft:scaffolding":8,"minecraft:written_book":2,"minecraft:dark_oak_pressure_plate":6,"minecraft:iron_trapdoor":19,"minecraft:furnace":1,"minecraft:egg":1,"minecraft:gray_banner":13,"minecraft:stone_pressure_plate":1,"minecraft:water_bucket":20,"minecraft:dark_oak_stairs":577,"minecraft:mossy_stone_bricks":1,"minecraft:end_rod":5,"minecraft:spruce_door":3,"minecraft:prismarine_brick_slab":15,"minecraft:polished_andesite":2,"minecraft:acacia_trapdoor":5,"minecraft:dark_oak_sign":2,"minecraft:oak_planks":3,"minecraft:blue_wool":2,"minecraft:mossy_stone_brick_stairs":7,"minecraft:redstone_block":4,"minecraft:spruce_sign":1,"minecraft:cracked_stone_bricks":3,"minecraft:oak_leaves":35,"minecraft:white_wool":104,"minecraft:dark_oak_trapdoor":2,"minecraft:crafting_table":2,"minecraft:sand":1,"minecraft:dark_prismarine_slab":2,"minecraft:comparator":3,"minecraft:oak_slab":205,"minecraft:loom":6,"minecraft:black_banner":2,"minecraft:crossbow":18,"minecraft:white_bed":12,"minecraft:dark_oak_fence_gate":1,"minecraft:chiseled_quartz_block":10,"minecraft:lingering_potion":106,"minecraft:note_block":8,"minecraft:painting":82,"minecraft:spruce_log":1,"minecraft:smoker":3,"minecraft:dark_oak_door":1,"minecraft:redstone_torch":2,"minecraft:oak_log":197,"minecraft:flower_pot":3,"minecraft:dark_prismarine":37,"minecraft:lever":67,"minecraft:black_concrete":95,"minecraft:acacia_door":11,"minecraft:gray_shulker_box":5,"minecraft:dark_oak_log":3,"minecraft:command_block":59,"minecraft:sunflower":19,"minecraft:heavy_weighted_pressure_plate":3,"minecraft:barrier":5,"minecraft:stone_button":21,"minecraft:lectern":1,"minecraft:oak_pressure_plate":5,"minecraft:iron_door":3,"minecraft:blue_carpet":41,"minecraft:diamond_sword":9,"minecraft:fishing_rod":55,"minecraft:white_banner":15,"minecraft:acacia_pressure_plate":2,"minecraft:stripped_oak_wood":7,"minecraft:dark_oak_fence":4,"minecraft:grass_path":34,"minecraft:chain_command_block":3,"minecraft:glass_pane":29,"minecraft:repeating_command_block":58,"minecraft:oak_boat":2,"minecraft:white_concrete":205,"minecraft:jukebox":4,"minecraft:smooth_stone":3,"minecraft:splash_potion":213,"minecraft:cobweb":5},"minecraft:killed_by":{"minecraft:player":4,"minecraft:iron_golem":8},"minecraft:killed":{"minecraft:spider":1,"minecraft:slime":4,"minecraft:skeleton":1,"minecraft:iron_golem":1,"minecraft:bat":1,"minecraft:wandering_trader":1,"minecraft:creeper":1,"minecraft:trader_llama":2,"minecraft:zombie":1},"minecraft:mined":{"minecraft:white_bed":11},"minecraft:dropped":{"minecraft:spruce_sign":1,"minecraft:repeating_command_block":1,"minecraft:porkchop":1,"minecraft:black_dye":63,"minecraft:diamond_leggings":4,"minecraft:crossbow":1,"minecraft:feather":3,"minecraft:flower_banner_pattern":1,"minecraft:grass_block":3,"minecraft:red_carpet":3,"minecraft:emerald":1,"minecraft:dark_oak_leaves":1,"minecraft:repeater":2,"minecraft:wooden_axe":7,"minecraft:diamond_helmet":3,"minecraft:gold_nugget":65,"minecraft:writable_book":8,"minecraft:bone_meal":64,"minecraft:white_banner":1,"minecraft:black_concrete":1,"minecraft:gray_dye":1,"minecraft:dandelion":1,"minecraft:gold_ingot":3,"minecraft:bone":2,"minecraft:redstone":2,"minecraft:gravel":1,"minecraft:jungle_pressure_plate":1,"minecraft:lever":2,"minecraft:grass_path":1,"minecraft:chicken":1,"minecraft:birch_pressure_plate":1,"minecraft:orange_wool":1,"minecraft:totem_of_undying":80,"minecraft:diamond_sword":2,"minecraft:tipped_arrow":1,"minecraft:turtle_helmet":1,"minecraft:stone":455,"minecraft:diamond_chestplate":2,"minecraft:quartz_block":1,"minecraft:glowstone":1,"minecraft:chest":8,"minecraft:diamond_boots":3,"minecraft:bow":1,"minecraft:splash_potion":1},"minecraft:picked_up":{"minecraft:wooden_axe":9,"minecraft:azure_bluet":2,"minecraft:splash_potion":1,"minecraft:chicken":2,"minecraft:nether_wart":3,"minecraft:leather_leggings":1,"minecraft:diamond_sword":1,"minecraft:enchanted_book":1,"minecraft:acacia_pressure_plate":1,"minecraft:golden_sword":1,"minecraft:flint_and_steel":2,"minecraft:snow":2,"minecraft:item_frame":2,"minecraft:oak_sign":1,"minecraft:diamond_leggings":10,"minecraft:gold_nugget":1,"minecraft:dark_oak_leaves":1,"minecraft:oak_boat":1,"minecraft:written_book":3,"minecraft:poppy":3,"minecraft:chest":84,"minecraft:egg":2,"minecraft:tipped_arrow":4,"minecraft:dark_oak_sapling":2,"minecraft:stick":4,"minecraft:stone":495,"minecraft:torch":4,"minecraft:gray_dye":1,"minecraft:porkchop":2,"minecraft:stone_button":7,"minecraft:redstone":3,"minecraft:gray_shulker_box":2,"minecraft:blue_carpet":1,"minecraft:dark_oak_planks":1,"minecraft:black_dye":63,"minecraft:quartz_block":1,"minecraft:repeating_command_block":1,"minecraft:red_shulker_box":1,"minecraft:diamond_chestplate":8,"minecraft:diamond_boots":9,"minecraft:glowstone":1,"minecraft:saddle":2,"minecraft:gold_ingot":5,"minecraft:totem_of_undying":29,"minecraft:oxeye_daisy":1,"minecraft:barrier":3,"minecraft:feather":3,"minecraft:jungle_pressure_plate":1,"minecraft:repeater":13,"minecraft:lily_pad":4,"minecraft:dirt":1,"minecraft:white_banner":5,"minecraft:lantern":2,"minecraft:birch_pressure_plate":1,"minecraft:red_carpet":4,"minecraft:bone":2,"minecraft:bow":1,"minecraft:wheat_seeds":11,"minecraft:bell":10,"minecraft:iron_ingot":15,"minecraft:diamond_helmet":9,"minecraft:bamboo":116,"minecraft:dark_oak_stairs":1,"minecraft:dandelion":2,"minecraft:grass_path":1,"minecraft:ink_sac":2,"minecraft:grass_block":4,"minecraft:spider_eye":1,"minecraft:orange_wool":1,"minecraft:slime_ball":15,"minecraft:diamond":51,"minecraft:gray_banner":1,"minecraft:lever":6,"minecraft:writable_book":8,"minecraft:chainmail_leggings":18,"minecraft:crossbow":73,"minecraft:bone_meal":64,"minecraft:golden_horse_armor":1,"minecraft:emerald":72,"minecraft:sunflower":13},"minecraft:crafted":{"minecraft:leather_leggings":5,"minecraft:leather_helmet":2,"minecraft:leather_chestplate":3}},"DataVersion":1976}